codeany_mcp_server/__init__.py
codeany_mcp_server/auth_guard.py
codeany_mcp_server/client_factory.py
codeany_mcp_server/config.py
codeany_mcp_server/errors.py
codeany_mcp_server/io_utils.py
codeany_mcp_server/logging_config.py
codeany_mcp_server/main.py
codeany_mcp_server/router.py
codeany_mcp_server/types.py
codeany_mcp_server/handlers/__init__.py
codeany_mcp_server/handlers/_utils.py
codeany_mcp_server/handlers/capabilities.py
codeany_mcp_server/handlers/examples.py
codeany_mcp_server/handlers/hubs.py
codeany_mcp_server/handlers/io_checker.py
codeany_mcp_server/handlers/limits.py
codeany_mcp_server/handlers/mcq.py
codeany_mcp_server/handlers/meta.py
codeany_mcp_server/handlers/statements.py
codeany_mcp_server/handlers/system.py
codeany_mcp_server/handlers/tasks_core.py
codeany_mcp_server/handlers/tests.py
codeany_mcp_server/handlers/testsets.py
codeany_hubs_mcp_server-0.0.3.4.dist-info/METADATA
codeany_hubs_mcp_server-0.0.3.4.dist-info/WHEEL
codeany_hubs_mcp_server-0.0.3.4.dist-info/entry_points.txt
codeany_hubs_mcp_server-0.0.3.4.dist-info/RECORD
