Metadata-Version: 2.4
Name: codeany-hubs-mcp-server
Version: 0.0.3.4
Summary: MCP server exposing Codeany Hubs authoring tools.
License: MIT
Requires-Python: >=3.9
Requires-Dist: codeany-hub<0.3.0,>=0.2.2.9
Requires-Dist: typing-extensions>=4.7.0
Provides-Extra: dev
Requires-Dist: mypy>=1.8.0; extra == 'dev'
Requires-Dist: pytest-httpx>=0.30.0; extra == 'dev'
Requires-Dist: pytest>=8.0.0; extra == 'dev'
Requires-Dist: ruff>=0.3.0; extra == 'dev'
